cdk8s/__init__.py
cdk8s/py.typed
cdk8s/_jsii/__init__.py
cdk8s/_jsii/cdk8s@2.70.43.jsii.tgz
cdk8s-2.70.43.dist-info/LICENSE
cdk8s-2.70.43.dist-info/METADATA
cdk8s-2.70.43.dist-info/NOTICE
cdk8s-2.70.43.dist-info/WHEEL
cdk8s-2.70.43.dist-info/top_level.txt
cdk8s-2.70.43.dist-info/RECORD
