Metadata-Version: 2.1
Name: cdk8s
Version: 2.70.43
Summary: This is the core library of Cloud Development Kit (CDK) for Kubernetes (cdk8s). cdk8s apps synthesize into standard Kubernetes manifests which can be applied to any Kubernetes cluster.
Home-page: https://github.com/cdk8s-team/cdk8s-core.git
Author: Amazon Web Services
License: Apache-2.0
Project-URL: Source, https://github.com/cdk8s-team/cdk8s-core.git
Classifier: Intended Audience :: Developers
Classifier: Operating System :: OS Independent
Classifier: Programming Language :: JavaScript
Classifier: Programming Language :: Python :: 3 :: Only
Classifier: Programming Language :: Python :: 3.9
Classifier: Programming Language :: Python :: 3.10
Classifier: Programming Language :: Python :: 3.11
Classifier: Typing :: Typed
Classifier: Development Status :: 5 - Production/Stable
Classifier: License :: OSI Approved
Requires-Python: ~=3.9
License-File: LICENSE
License-File: NOTICE
Requires-Dist: constructs <11.0.0,>=10.0.0
Requires-Dist: jsii <2.0.0,>=1.125.0
Requires-Dist: publication >=0.0.3
Requires-Dist: typeguard ==2.13.3
